{
  "questions": [
    {
      "id": "Q001",
      "category": "南湖红船",
      "text": "南湖红船与中国近现代史中的哪一次重要会议密切相关？",
      "options": [
        "中共一大",
        "遵义会议",
        "八七会议",
        "古田会议"
      ],
      "answerIndex": 0,
      "explain": "中共一大最后一天的会议转移到嘉兴南湖红船上举行，南湖红船也因此成为重要的红色文化符号。"
    },
    {
      "id": "Q002",
      "category": "五芳斋",
      "text": "嘉兴最有代表性的传统美食之一，五芳斋最出名的产品是什么？",
      "options": [
        "粽子",
        "月饼",
        "汤圆",
        "青团"
      ],
      "answerIndex": 0,
      "explain": "五芳斋以嘉兴粽子闻名，非常适合在游戏里作为嘉兴风物主题。"
    },
    {
      "id": "Q003",
      "category": "蓝印花布",
      "text": "蓝印花布最典型的传统配色是什么？",
      "options": [
        "蓝白",
        "红黑",
        "金紫",
        "橙绿"
      ],
      "answerIndex": 0,
      "explain": "蓝印花布常以蓝白对比形成朴素、清晰的传统纹样。"
    },
    {
      "id": "Q004",
      "category": "马家浜文化",
      "text": "马家浜文化通常属于哪一历史阶段的考古文化？",
      "options": [
        "新石器时代",
        "秦汉时期",
        "唐宋时期",
        "明清时期"
      ],
      "answerIndex": 0,
      "explain": "马家浜文化是江南地区重要的新石器时代文化。"
    },
    {
      "id": "Q005",
      "category": "月河历史街区",
      "text": "月河历史街区最适合用哪种意象来概括？",
      "options": [
        "水乡老街与市集",
        "沙漠驿站",
        "雪山营地",
        "海岛灯塔"
      ],
      "answerIndex": 0,
      "explain": "月河历史街区以老街、河道、石桥和市集生活气息著称。"
    },
    {
      "id": "Q006",
      "category": "嘉兴车站",
      "text": "嘉兴站和嘉兴南站在地图里最适合归类为什么类型的地产？",
      "options": [
        "交通主题地产",
        "古代书院",
        "戏曲舞台",
        "山地牧场"
      ],
      "answerIndex": 0,
      "explain": "两座车站都属于嘉兴的重要交通节点，因此作为交通主题地产最直观。"
    },
    {
      "id": "Q007",
      "category": "海宁观潮",
      "text": "海宁观潮主要与哪条江的潮水景观有关？",
      "options": [
        "钱塘江",
        "黄河",
        "珠江",
        "松花江"
      ],
      "answerIndex": 0,
      "explain": "海宁观潮最知名的就是钱塘江大潮。"
    },
    {
      "id": "Q008",
      "category": "乌镇水乡",
      "text": "乌镇最适合用哪组关键词来描述？",
      "options": [
        "江南水乡",
        "高原草原",
        "热带雨林",
        "边塞大漠"
      ],
      "answerIndex": 0,
      "explain": "乌镇是典型的江南水乡古镇，河道、白墙黛瓦和桥巷是它的代表形象。"
    },
    {
      "id": "Q009",
      "category": "大运河长虹桥",
      "text": "大运河长虹桥最适合体现哪种文化意象？",
      "options": [
        "运河桥梁与水路交通",
        "火山地貌",
        "草原放牧",
        "海底珊瑚"
      ],
      "answerIndex": 0,
      "explain": "长虹桥与大运河主题最适合表现桥梁、水路和往来商旅。"
    },
    {
      "id": "Q010",
      "category": "子城遗址",
      "text": "子城遗址在游戏中更适合作为哪种主题？",
      "options": [
        "古城历史遗存",
        "现代机场",
        "海上油田",
        "动物乐园"
      ],
      "answerIndex": 0,
      "explain": "子城遗址适合作为古城历史遗存主题的代表地产。"
    }
  ]
}
